lab4/barrel_shifter/barrelShifter.v
module shift_reg #(parameter MSB=8) 
( 
    input d,
    input clk,
    input en,
    input dir,
    input rstn,
    output reg [MSB-1:0] out
);

always @ (posedge clk)
    if (!rstn)
        out <= 0;
    else begin
    if (en)
    case (dir)
    0 : out <= {out[MSB-2:0], d};
    1 : out <= {d, out[MSB-1:1]};
    endcase
else
    out <= out;
    end
endmodule

barrel_shifter/barrelShifter_tb.v
    module tb_br;  
       parameter MSB = 16;        // [Optional] Declare a parameter to represent number of bits in shift register  
    
    reg data;                  // Declare a variable to drive d-input of design  
    reg clk;                   // Declare a variable to drive clock to the design  
    reg en;                    // Declare a variable to drive enable to the design  
    reg dir;                   // Declare a variable to drive direction of shift register  
    reg rstn;                  // Declare a variable to drive reset to the design  
    wire [MSB-1:0] out;        // Declare a wire to capture output from the design  
    
    // Instantiate design (16-bit shift register) by passing MSB and connect with TB signals  
    shift_reg  #(MSB) sr0  (  .d (data),  
                                .clk (clk),  
                                .en (en),  
                                .dir (dir),  
                                .rstn (rstn),  
                                .out (out));  
    
    // Generate clock time period = 20ns, freq => 50MHz  
    always #10 clk = ~clk;  
    
    initial begin  
        clk <= 0;  
        en <= 0;  
        dir <= 0;  
        rstn <= 0;  
        data <= 'h1;  
    end  
    
    initial begin  
    
        rstn <= 0;  
        #20 rstn <= 1;  
            en <= 1;  
    
        repeat (7) @ (posedge clk)  
            data <= ~data;  
    
        #10 dir <= 1;  
        repeat (7) @ (posedge clk)  
            data <= ~data;  
    
        repeat (7) @ (posedge clk);  
    
        $finish;  
    end  
    
    Initial  
        $monitor ("rstn=%0b data=%b, en=%0b, dir=%0b, out=%b", rstn, data, en, dir, out);  
endmodule

lab4/barrel_shifter/sim/dump.vcd
$date
	Fri Dec 08 04:46:47 2023
$end
$version
	Icarus Verilog
$end
$timescale
	1s
$end
$scope module tb_br $end
$var wire 16 ! out [15:0] $end
$var parameter 32 " MSB $end
$var reg 1 # clk $end
$var reg 1 $ data $end
$var reg 1 % dir $end
$var reg 1 & en $end
$var reg 1 ' rstn $end
$scope module sr0 $end
$var wire 1 # clk $end
$var wire 1 $ d $end
$var wire 1 % dir $end
$var wire 1 & en $end
$var wire 1 ' rstn $end
$var parameter 32 ( MSB $end
$var reg 16 ) out [15:0] $end
$upscope $end
$upscope $end
$enddefinitions $end
$comment Show the parameter values. $end
$dumpall
b10000 (
b10000 "
$end
#0
$dumpvars
bx )
0'
0&
0%
1$
0#
bx !
$end
#10
b0 !
b0 )
1#
#20
1&
1'
0#
#30
b1 !
b1 )
0$
1#
#40
0#
#50
1$
b10 !
b10 )
1#
#60
0#
#70
b101 !
b101 )
0$
1#
#80
0#
#90
1$
b1010 !
b1010 )
1#
#100
0#
#110
b10101 !
b10101 )
0$
1#
#120
0#
#130
1$
b101010 !
b101010 )
1#
#140
0#
#150
b1010101 !
b1010101 )
0$
1#
#160
1%
0#
#170
b101010 !
b101010 )
1$
1#
#180
0#
#190
0$
b1000000000010101 !
b1000000000010101 )
1#
#200
0#
#210
b100000000001010 !
b100000000001010 )
1$
1#
#220
0#
#230
0$
b1010000000000101 !
b1010000000000101 )
1#
#240
0#
#250
b101000000000010 !
b101000000000010 )
1$
1#
#260
0#
#270
0$
b1010100000000001 !
b1010100000000001 )
1#
#280
0#
#290
b101010000000000 !
b101010000000000 )
1$
1#
#300
0#
#310
b1010101000000000 !
b1010101000000000 )
1#
#320
0#
#330
b1101010100000000 !
b1101010100000000 )
1#
#340
0#
#350
b1110101010000000 !
b1110101010000000 )
1#
#360
0#
#370
b1111010101000000 !
b1111010101000000 )
1#
#380
0#
#390
b1111101010100000 !
b1111101010100000 )
1#
#400
0#
#410
b1111110101010000 !
b1111110101010000 )
1#
#420
0#
#430
b1111111010101000 !
b1111111010101000 )
1#
