lab4/universal_shift_reg/universal_shift_reg.v
// Универсальный регистр сдвига с параллельным входом, параллельным выходом,
// последовательным выходом с синхронной загрузкой данных

module shift_reg(
  input clk, rst_n, 
  input [1:0] select, 	// select operation
  input [3:0] p_din,  	// parallel data in 
  input s_left_din,   	// serial left data in
  input s_right_din,  	// serial right data in
  output reg [3:0] p_dout, //parallel data out
  output s_left_dout, 	// serial left data out
  output s_right_dout 	// serial right data out
);
always@(posedge clk) begin
    if(!rst_n) p_dout <= 0;
    else begin
    case(select)
        2'h1: p_dout <= {s_right_din,p_dout[3:1]}; // Right Shift
        2'h2: p_dout <= {p_dout[2:0],s_left_din};  // Left Shift
        2'h3: p_dout <= p_din; 							// Parallel in - Parallel out
        default: p_dout <= p_dout; 						// Do nothing
    endcase
        end
    end
    assign s_left_dout = p_dout[0];
    assign s_right_dout = p_dout[3];
endmodule

lab4/universal_shift_reg/universal_shift_reg_tb.v
//
//	тестбенч для универсального регистра сдвига

module TB;
    reg clk, rst_n;
    reg [1:0] select;
    reg [3:0] p_din;
    reg s_left_din, s_right_din;
    wire [3:0] p_dout; //parallel data out
    wire s_left_dout, s_right_dout;

    shift_reg usr(clk, rst_n, select, p_din, s_left_din, s_right_din, p_dout, s_left_dout, s_right_dout);

    always #2 clk = ~clk;
    initial begin
    $monitor("select=%b, p_din=%b, s_left_din=%b, s_right_din=%b --> p_dout = %b, s_left_dout = %b, s_right_dout = %b",
                select, p_din, s_left_din, s_right_din, p_dout, s_left_dout, s_right_dout);
    clk = 0; rst_n = 0;
    #3 rst_n = 1;

    p_din = 4'b1101;
    s_left_din = 1'b1;
    s_right_din = 1'b0;

    select = 2'h3; #10;
    select = 2'h1; #20;
    p_din = 4'b1101;
    select = 2'h3; #10;
    select = 2'h2; #20;
    select = 2'h0; #20;

    $finish;
    end
    // To enable waveform
    initial begin 
    $dumpfile("dump.vcd"); $dumpvars;
    end

endmodule

lab4/universal_shift_reg/sim/dump.vcd
$date
	Sat Dec 09 11:17:58 2023
$end
$version
	Icarus Verilog
$end
$timescale
	1s
$end
$scope module TB $end
$var wire 1 ! s_right_dout $end
$var wire 1 " s_left_dout $end
$var wire 4 # p_dout [3:0] $end
$var reg 1 $ clk $end
$var reg 4 % p_din [3:0] $end
$var reg 1 & rst_n $end
$var reg 1 ' s_left_din $end
$var reg 1 ( s_right_din $end
$var reg 2 ) select [1:0] $end
$scope module usr $end
$var wire 1 $ clk $end
$var wire 4 * p_din [3:0] $end
$var wire 1 & rst_n $end
$var wire 1 ' s_left_din $end
$var wire 1 ( s_right_din $end
$var wire 2 + select [1:0] $end
$var wire 1 ! s_right_dout $end
$var wire 1 " s_left_dout $end
$var reg 4 , p_dout [3:0] $end
$upscope $end
$upscope $end
$enddefinitions $end
$comment Show the parameter values. $end
$dumpall
$end
#0
$dumpvars
bx ,
bx +
bx *
bx )
x(
x'
0&
bx %
0$
bx #
x"
x!
$end
#2
0"
0!
b0 #
b0 ,
1$
#3
b11 )
b11 +
0(
1'
b1101 %
b1101 *
1&
#4
0$
#6
1"
1!
b1101 #
b1101 ,
1$
#8
0$
#10
1$
#12
0$
#13
b1 )
b1 +
#14
0"
0!
b110 #
b110 ,
1$
#16
0$
#18
1"
b11 #
b11 ,
1$
#20
0$
#22
b1 #
b1 ,
1$
#24
0$
#26
0"
b0 #
b0 ,
1$
#28
0$
#30
1$
#32
0$
#33
b11 )
b11 +
#34
1"
1!
b1101 #
b1101 ,
1$
#36
0$
#38
1$
#40
0$
#42
1$
#43
b10 )
b10 +
#44
0$
#46
b1011 #
b1011 ,
1$
#48
0$
#50
0!
b111 #
b111 ,
1$
#52
0$
#54
1!
b1111 #
b1111 ,
1$
#56
0$
#58
1$
#60
0$
#62
1$
#63
b0 )
b0 +
