SIPO/SIPO.v
module sipo_4bit #(parameter WIDTH=4) (input wire clk, input wire reset, input wire data_in, input wire enable,
                                      input wire set_all_ones, output reg [WIDTH-1:0] data_out);

  always @(posedge clk or posedge reset) begin
    if (reset)
      data_out <= {WIDTH{1'b0}};  // Сброс данных при сигнале reset
    else if (enable) begin
      if (set_all_ones)
        data_out <= {WIDTH{1'b1}};  // Установка всех разрядов в 1
      else
        data_out <= {data_out[WIDTH-2:0], data_in};  // Загрузка данных в первый разряд
    end
  end

endmodule

SIPO/SIPO_tb.v
module sipo_4bit_tb;
  parameter WIDTH = 4;

  reg clk;
  reg reset;
  reg data_in;
  reg enable;
  reg set_all_ones;
  wire [WIDTH-1:0] data_out;

  sipo_4bit #(WIDTH) dut (
    .clk(clk),
    .reset(reset),
    .data_in(data_in),
    .enable(enable),
    .set_all_ones(set_all_ones),
    .data_out(data_out)
  );

  always #5 clk = ~clk;  // Генерация тактового сигнала

  initial begin
    clk = 1'b0;
    reset = 1'b1;
    data_in = 1'b0;
    enable = 1'b0;
    set_all_ones = 1'b0;

    #10 reset = 1'b0;  // Сброс сигнала reset
    #10 enable = 1'b1;  // Разрешение загрузки данных

    // Тестовые векторы
    #10 data_in = 1'b1;  // Загрузка 1 в первый разряд
    #10 data_in = 1'b0;  // Загрузка 0 в первый разряд
    #10 data_in = 1'b1;  // Загрузка 1 в первый разряд

    #10 set_all_ones = 1'b1;  // Установка всех разрядов в 1
    #10 set_all_ones = 1'b0;

    #10 enable = 1'b0;  // Загрузка данных отключена

    #10 $finish;  // Окончание симуляции
  end

  initial begin
    $dumpfile("dump.vcd");  // Запись VCD-файла для отладки
    $dumpvars(0, sipo_4bit_tb);  // Запись переменных в VCD-файл
    $monitor($time, "data_out = %b", data_out);  // Вывод значения data_out во время симуляции
  end

endmodule

SIPO/sim/dump.vcd
$date
	Fri Dec 08 04:27:51 2023
$end
$version
	Icarus Verilog
$end
$timescale
	1s
$end
$scope module sipo_4bit_tb $end
$var wire 4 ! data_out [3:0] $end
$var parameter 32 " WIDTH $end
$var reg 1 # clk $end
$var reg 1 $ data_in $end
$var reg 1 % enable $end
$var reg 1 & reset $end
$var reg 1 ' set_all_ones $end
$scope module dut $end
$var wire 1 # clk $end
$var wire 1 $ data_in $end
$var wire 1 % enable $end
$var wire 1 & reset $end
$var wire 1 ' set_all_ones $end
$var parameter 32 ( WIDTH $end
$var reg 4 ) data_out [3:0] $end
$upscope $end
$upscope $end
$enddefinitions $end
$comment Show the parameter values. $end
$dumpall
b100 (
b100 "
$end
#0
$dumpvars
b0 )
0'
1&
0%
0$
0#
b0 !
$end
#5
1#
#10
0#
0&
#15
1#
#20
0#
1%
#25
1#
#30
0#
1$
#35
b1 !
b1 )
1#
#40
0#
0$
#45
b10 !
b10 )
1#
#50
0#
1$
#55
b101 !
b101 )
1#
#60
0#
1'
#65
b1111 !
b1111 )
1#
#70
0#
0'
#75
1#
#80
0#
0%
