lab4/DOP_TASK/shift_reg.v
module shift_reg #(parameter WIDTH = 8) (
    input clk,
    input rst_n,
    input data_in,
    input shift_en,
    output reg [3:0] seg_out,
    output reg [WIDTH-1:0] data_out
);

    always @(posedge clk or negedge rst_n) begin
        if (!rst_n)
            data_out <= {WIDTH{1'b0}};
        else if (shift_en)
            data_out <= {data_in,data_out[WIDTH-1:1]};
    end
    
    always @(posedge clk) begin
        if (shift_en)
            seg_out <= data_out[WIDTH-1:WIDTH-4];
    end

endmodule // shift_reg

lab4/DOP_TASK/testbench.v
module testbench;

localparam WIDTH = 8;

reg clk;
reg rst_n;
reg shift_en;
reg data_in;
wire [3:0] seg_out;
wire [WIDTH-1:0] data_out;
  
shift_reg #(WIDTH) shft (
    .clk (clk),
    .rst_n (rst_n),
    .data_in (data_in),
    .shift_en (shift_en),
    .seg_out (seg_out),
    .data_out (data_out)
);

// Генерация тактового сигнала
initial begin
    clk = 0;
    forever #4 clk = ~clk;
end

// Функция для генерации последовательности значений
task push;
begin
    $display("########## Shift enable active ##########");
    shift_en = 1'b1;
    repeat(9) begin
        @(negedge clk)
        data_in = $urandom % 2;
    end
    shift_en = 1'b0;
    $display("########## Shift enable disable ##########\n");
end
endtask

// Функция для сброса
task async_rst;
begin
    $display("########## RESET start! ##########");
    #10 rst_n = 1'b0;
    #10 rst_n = 1'b1;
    $display("########## RESET finish!\n ##########");
end
endtask

initial begin
    $dumpfile("waveform.vcd");
    $dumpvars();
    
    $display("#################### Starting simulation ####################");
    
    shift_en = 1'b0;
    rst_n = 1'b1;
    data_in = 1'b0;
    
    // Сброс
    async_rst();
    
    // Генерация последовательности
    repeat(10) begin
        #50 push;
    end
    
    #200 $finish;
end

// Отслеживание выходных значений
always @(posedge clk) begin
    $display("@time=%0t\tseg_out=%d\tdata_out=0x%h\t", $time, seg_out, data_out);
end


  initial begin
    $dumpfile("dump.vcd");  // Запись VCD-файла для отладки
    $dumpvars(0, testbench);  // Запись переменных в VCD-файл
    $monitor($time, "data_out = %b", data_out);  // Вывод значения data_out во время симуляции
  end

endmodule // testbench

lab4/DOP_TASK/sim/waveform.vcd
$date
	Sat Dec 09 03:09:47 2023
$end
$version
	Icarus Verilog
$end
$timescale
	1s
$end
$scope module testbench $end
$var wire 4 ! seg_out [3:0] $end
$var wire 8 " data_out [7:0] $end
$var parameter 32 # WIDTH $end
$var reg 1 $ clk $end
$var reg 1 % data_in $end
$var reg 1 & rst_n $end
$var reg 1 ' shift_en $end
$scope module shft $end
$var wire 1 $ clk $end
$var wire 1 % data_in $end
$var wire 1 & rst_n $end
$var wire 1 ' shift_en $end
$var parameter 32 ( WIDTH $end
$var reg 8 ) data_out [7:0] $end
$var reg 4 * seg_out [3:0] $end
$upscope $end
$scope task async_rst $end
$upscope $end
$scope task push $end
$upscope $end
$upscope $end
$scope module testbench $end
$scope module shft $end
$upscope $end
$scope task async_rst $end
$upscope $end
$scope task push $end
$upscope $end
$upscope $end
$enddefinitions $end
$comment Show the parameter values. $end
$dumpall
b1000 (
b1000 #
$end
#0
$dumpvars
bx *
bx )
0'
1&
0%
0$
bx "
bx !
$end
#4
1$
#8
0$
#10
b0 "
b0 )
0&
#12
1$
#16
0$
#20
1$
1&
#24
0$
#28
1$
#32
0$
#36
1$
#40
0$
#44
1$
#48
0$
#52
1$
#56
0$
#60
1$
#64
0$
#68
1$
#70
1'
#72
0$
#76
b0 !
b0 *
1$
#80
1%
0$
#84
b10000000 "
b10000000 )
1$
#88
0$
#92
b1000 !
b1000 *
b11000000 "
b11000000 )
1$
#96
0$
#100
b1100 !
b1100 *
b11100000 "
b11100000 )
1$
#104
0$
#108
b1110 !
b1110 *
b11110000 "
b11110000 )
1$
#112
0$
#116
b1111 !
b1111 *
b11111000 "
b11111000 )
1$
#120
0$
#124
b11111100 "
b11111100 )
1$
#128
0%
0$
#132
b1111110 "
b1111110 )
1$
#136
0'
1%
0$
#140
1$
#144
0$
#148
1$
#152
0$
#156
1$
#160
0$
#164
1$
#168
0$
#172
1$
#176
0$
#180
1$
#184
0$
#186
1'
#188
b111 !
b111 *
b10111111 "
b10111111 )
1$
#192
0$
#196
b1011 !
b1011 *
b11011111 "
b11011111 )
1$
#200
0%
0$
#204
b1101 !
b1101 *
b1101111 "
b1101111 )
1$
#208
1%
0$
#212
b110 !
b110 *
b10110111 "
b10110111 )
1$
#216
0$
#220
b1011 !
b1011 *
b11011011 "
b11011011 )
1$
#224
0%
0$
#228
b1101 !
b1101 *
b1101101 "
b1101101 )
1$
#232
1%
0$
#236
b110 !
b110 *
b10110110 "
b10110110 )
1$
#240
0%
0$
#244
b1011 !
b1011 *
b1011011 "
b1011011 )
1$
#248
1%
0$
#252
b101 !
b101 *
b10101101 "
b10101101 )
1$
#256
0'
0%
0$
#260
1$
#264
0$
#268
1$
#272
0$
#276
1$
#280
0$
#284
1$
#288
0$
#292
1$
#296
0$
#300
1$
#304
0$
#306
1'
#308
b1010 !
b1010 *
b1010110 "
b1010110 )
1$
#312
1%
0$
#316
b101 !
b101 *
b10101011 "
b10101011 )
1$
#320
0$
#324
b1010 !
b1010 *
b11010101 "
b11010101 )
1$
#328
0%
0$
#332
b1101 !
b1101 *
b1101010 "
b1101010 )
1$
#336
1%
0$
#340
b110 !
b110 *
b10110101 "
b10110101 )
1$
#344
0%
0$
#348
b1011 !
b1011 *
b1011010 "
b1011010 )
1$
#352
0$
#356
b101 !
b101 *
b101101 "
b101101 )
1$
#360
0$
#364
b10 !
b10 *
b10110 "
b10110 )
1$
#368
1%
0$
#372
b1 !
b1 *
b10001011 "
b10001011 )
1$
#376
0'
0%
0$
#380
1$
#384
0$
#388
1$
#392
0$
#396
1$
#400
0$
#404
1$
#408
0$
#412
1$
#416
0$
#420
1$
#424
0$
#426
1'
#428
b1000 !
b1000 *
b1000101 "
b1000101 )
1$
#432
1%
0$
#436
b100 !
b100 *
b10100010 "
b10100010 )
1$
#440
0$
#444
b1010 !
b1010 *
b11010001 "
b11010001 )
1$
#448
0$
#452
b1101 !
b1101 *
b11101000 "
b11101000 )
1$
#456
0$
#460
b1110 !
b1110 *
b11110100 "
b11110100 )
1$
#464
0%
0$
#468
b1111 !
b1111 *
b1111010 "
b1111010 )
1$
#472
0$
#476
b111 !
b111 *
b111101 "
b111101 )
1$
#480
0$
#484
b11 !
b11 *
b11110 "
b11110 )
1$
#488
0$
#492
b1 !
b1 *
b1111 "
b1111 )
1$
#496
0'
1%
0$
#500
1$
#504
0$
#508
1$
#512
0$
#516
1$
#520
0$
#524
1$
#528
0$
#532
1$
#536
0$
#540
1$
#544
0$
#546
1'
#548
b0 !
b0 *
b10000111 "
b10000111 )
1$
#552
0%
0$
#556
b1000 !
b1000 *
b1000011 "
b1000011 )
1$
#560
1%
0$
#564
b100 !
b100 *
b10100001 "
b10100001 )
1$
#568
0$
#572
b1010 !
b1010 *
b11010000 "
b11010000 )
1$
#576
0$
#580
b1101 !
b1101 *
b11101000 "
b11101000 )
1$
#584
0$
#588
b1110 !
b1110 *
b11110100 "
b11110100 )
1$
#592
0$
#596
b1111 !
b1111 *
b11111010 "
b11111010 )
1$
#600
0%
0$
#604
b1111101 "
b1111101 )
1$
#608
0$
#612
b111 !
b111 *
b111110 "
b111110 )
1$
#616
0'
1%
0$
#620
1$
#624
0$
#628
1$
#632
0$
#636
1$
#640
0$
#644
1$
#648
0$
#652
1$
#656
0$
#660
1$
#664
0$
#666
1'
#668
b11 !
b11 *
b10011111 "
b10011111 )
1$
#672
0$
#676
b1001 !
b1001 *
b11001111 "
b11001111 )
1$
#680
0$
#684
b1100 !
b1100 *
b11100111 "
b11100111 )
1$
#688
0%
0$
#692
b1110 !
b1110 *
b1110011 "
b1110011 )
1$
#696
0$
#700
b111 !
b111 *
b111001 "
b111001 )
1$
#704
0$
#708
b11 !
b11 *
b11100 "
b11100 )
1$
#712
0$
#716
b1 !
b1 *
b1110 "
b1110 )
1$
#720
0$
#724
b0 !
b0 *
b111 "
b111 )
1$
#728
1%
0$
#732
b10000011 "
b10000011 )
1$
#736
0'
0%
0$
#740
1$
#744
0$
#748
1$
#752
0$
#756
1$
#760
0$
#764
1$
#768
0$
#772
1$
#776
0$
#780
1$
#784
0$
#786
1'
#788
b1000 !
b1000 *
b1000001 "
b1000001 )
1$
#792
0$
#796
b100 !
b100 *
b100000 "
b100000 )
1$
#800
1%
0$
#804
b10 !
b10 *
b10010000 "
b10010000 )
1$
#808
0$
#812
b1001 !
b1001 *
b11001000 "
b11001000 )
1$
#816
0%
0$
#820
b1100 !
b1100 *
b1100100 "
b1100100 )
1$
#824
0$
#828
b110 !
b110 *
b110010 "
b110010 )
1$
#832
0$
#836
b11 !
b11 *
b11001 "
b11001 )
1$
#840
0$
#844
b1 !
b1 *
b1100 "
b1100 )
1$
#848
0$
#852
b0 !
b0 *
b110 "
b110 )
1$
#856
0'
1%
0$
#860
1$
#864
0$
#868
1$
#872
0$
#876
1$
#880
0$
#884
1$
#888
0$
#892
1$
#896
0$
#900
1$
#904
0$
#906
1'
#908
b10000011 "
b10000011 )
1$
#912
0$
#916
b1000 !
b1000 *
b11000001 "
b11000001 )
1$
#920
0$
#924
b1100 !
b1100 *
b11100000 "
b11100000 )
1$
#928
0$
#932
b1110 !
b1110 *
b11110000 "
b11110000 )
1$
#936
0$
#940
b1111 !
b1111 *
b11111000 "
b11111000 )
1$
#944
0%
0$
#948
b1111100 "
b1111100 )
1$
#952
0$
#956
b111 !
b111 *
b111110 "
b111110 )
1$
#960
1%
0$
#964
b11 !
b11 *
b10011111 "
b10011111 )
1$
#968
0$
#972
b1001 !
b1001 *
b11001111 "
b11001111 )
1$
#976
0'
0$
#980
1$
#984
0$
#988
1$
#992
0$
#996
1$
#1000
0$
#1004
1$
#1008
0$
#1012
1$
#1016
0$
#1020
1$
#1024
0$
#1026
1'
#1028
b1100 !
b1100 *
b11100111 "
b11100111 )
1$
#1032
0%
0$
#1036
b1110 !
b1110 *
b1110011 "
b1110011 )
1$
#1040
0$
#1044
b111 !
b111 *
b111001 "
b111001 )
1$
#1048
1%
0$
#1052
b11 !
b11 *
b10011100 "
b10011100 )
1$
#1056
0$
#1060
b1001 !
b1001 *
b11001110 "
b11001110 )
1$
#1064
0%
0$
#1068
b1100 !
b1100 *
b1100111 "
b1100111 )
1$
#1072
1%
0$
#1076
b110 !
b110 *
b10110011 "
b10110011 )
1$
#1080
0$
#1084
b1011 !
b1011 *
b11011001 "
b11011001 )
1$
#1088
0%
0$
#1092
b1101 !
b1101 *
b1101100 "
b1101100 )
1$
#1096
0'
1%
0$
#1100
1$
#1104
0$
#1108
1$
#1112
0$
#1116
1$
#1120
0$
#1124
1$
#1128
0$
#1132
1$
#1136
0$
#1140
1$
#1144
0$
#1146
1'
#1148
b110 !
b110 *
b10110110 "
b10110110 )
1$
#1152
0$
#1156
b1011 !
b1011 *
b11011011 "
b11011011 )
1$
#1160
0$
#1164
b1101 !
b1101 *
b11101101 "
b11101101 )
1$
#1168
0%
0$
#1172
b1110 !
b1110 *
b1110110 "
b1110110 )
1$
#1176
1%
0$
#1180
b111 !
b111 *
b10111011 "
b10111011 )
1$
#1184
0$
#1188
b1011 !
b1011 *
b11011101 "
b11011101 )
1$
#1192
0%
0$
#1196
b1101 !
b1101 *
b1101110 "
b1101110 )
1$
#1200
0$
#1204
b110 !
b110 *
b110111 "
b110111 )
1$
#1208
0$
#1212
b11 !
b11 *
b11011 "
b11011 )
1$
#1216
0'
0$
